helpers/download.py
helpers/fetch_project_id_from_slug.py
helpers/fetch_versions.py
helpers/find_dependencies.py
helpers/find_project_meta.py
helpers/find_version.py
rinthdl/main.py
rinthdl/modpack.py
rinthdl/search.py
rinthdl-1.1.0.dist-info/LICENSE
rinthdl-1.1.0.dist-info/METADATA
rinthdl-1.1.0.dist-info/WHEEL
rinthdl-1.1.0.dist-info/entry_points.txt
rinthdl-1.1.0.dist-info/RECORD
