Metadata-Version: 2.1
Name: rinthdl
Version: 1.1.0
Summary: Define a Minecraft modpack in a JSON file, specifying mods, shaders, and resource packs, then download everything into organized folders for easy copying into your .minecraft folder.
License: GPL-3.0-only
Keywords: modrinth,minecraft,downloader
Author: Alexander Brightwater
Author-email: alexander.brightwater@gmail.com
Requires-Python: ==3.11.*
Classifier: License :: OSI Approved :: GNU General Public License v3 (GPLv3)
Classifier: Operating System :: OS Independent
Classifier: Programming Language :: Python :: 3
Classifier: Programming Language :: Python :: 3.11
Requires-Dist: requests (>=2.32.3,<3.0.0)
